{
  "resourceType" : "Bundle",
  "id" : "aeff2117-efbd-43df-a148-bafa8603cfbc",
  "meta" : {
    "lastUpdated" : "2021-02-23T17:10:12.345-07:00"
  },
  "type" : "collection",
  "entry" : [{
    "fullUrl" : "http://hl7.org/fhir/ca-bc/provider/ValueSet/ValidFlagVS",
    "resource" : {
      "resourceType" : "ValueSet",
      "id" : "ValidFlagVS",
      "text" : {
        "status" : "generated",
        "div" : "<div xmlns=\"http://www.w3.org/1999/xhtml\"><p>This value set contains 3 concepts</p><p style=\"border: black 1px dotted; background-color: #EEEEEE; padding: 8px; margin-bottom: 8px\">Expansion based on <a href=\"CodeSystem-ValidFlagCS.html\">BC Valid Flag Extension CodeSystem v0.1.0 (CodeSystem)</a></p><p>All codes from system <a href=\"CodeSystem-ValidFlagCS.html\"><code>http://hl7.org/fhir/ca-bc/provider/CodeSystem/ValidFlagCS</code></a></p><table class=\"codes\"><tr><td style=\"white-space:nowrap\"><b>Code</b></td><td><b>Display</b></td><td><b>Definition</b></td></tr><tr><td style=\"white-space:nowrap\"><a name=\"http---hl7.org-fhir-ca-bc-provider-CodeSystem-ValidFlagCS-valid\"> </a><a href=\"CodeSystem-ValidFlagCS.html#ValidFlagCS-valid\">valid</a></td><td/><td/></tr><tr><td style=\"white-space:nowrap\"><a name=\"http---hl7.org-fhir-ca-bc-provider-CodeSystem-ValidFlagCS-invalid\"> </a><a href=\"CodeSystem-ValidFlagCS.html#ValidFlagCS-invalid\">invalid</a></td><td/><td/></tr><tr><td style=\"white-space:nowrap\"><a name=\"http---hl7.org-fhir-ca-bc-provider-CodeSystem-ValidFlagCS-unknown\"> </a><a href=\"CodeSystem-ValidFlagCS.html#ValidFlagCS-unknown\">unknown</a></td><td/><td/></tr></table></div>"
      },
      "url" : "http://hl7.org/fhir/ca-bc/provider/ValueSet/ValidFlagVS",
      "version" : "0.1.0",
      "name" : "ValidFlagVS",
      "title" : "BC Valid Flag Extension ValueSet",
      "status" : "active",
      "date" : "2021-02-23T17:10:12-07:00",
      "publisher" : "BC Ministry of Health",
      "contact" : [{
        "name" : "BC Ministry of Health",
        "telecom" : [{
          "system" : "url",
          "value" : "https://www2.gov.bc.ca/gov/content/governments/organizational-structure/ministries-organizations/ministries/health"
        }]
      }],
      "description" : "An indication of the validity of a data element",
      "jurisdiction" : [{
        "coding" : [{
          "system" : "urn:iso:std:iso:3166",
          "code" : "CA",
          "display" : "Canada"
        }]
      }],
      "expansion" : {
        "identifier" : "urn:uuid:33a0622b-90f4-4eb9-8c0d-0d7263bf4a6e",
        "timestamp" : "2021-02-23T17:10:32-07:00",
        "total" : 3,
        "parameter" : [{
          "name" : "excludeNested",
          "valueBoolean" : false
        },
        {
          "name" : "version",
          "valueUri" : "http://hl7.org/fhir/ca-bc/provider/CodeSystem/ValidFlagCS|0.1.0"
        }],
        "contains" : [{
          "system" : "http://hl7.org/fhir/ca-bc/provider/CodeSystem/ValidFlagCS",
          "code" : "valid"
        },
        {
          "system" : "http://hl7.org/fhir/ca-bc/provider/CodeSystem/ValidFlagCS",
          "code" : "invalid"
        },
        {
          "system" : "http://hl7.org/fhir/ca-bc/provider/CodeSystem/ValidFlagCS",
          "code" : "unknown"
        }]
      }
    }
  }]
}